sp_tools/__init__.py
sp_tools/annotation/__init__.py
sp_tools/annotation/common.py
sp_tools/autosyspath/__init__.py
sp_tools/logger/__init__.py
sp_tools/logger/logger.py
sp_tools-0.0.4.dist-info/METADATA
sp_tools-0.0.4.dist-info/WHEEL
sp_tools-0.0.4.dist-info/top_level.txt
sp_tools-0.0.4.dist-info/zip-safe
sp_tools-0.0.4.dist-info/RECORD
