Metadata-Version: 2.1
Name: sp-tools
Version: 0.0.4
Summary: 为简化Python开发而生
Home-page: https://gitee.com/kingons/sp_tools
Author: dragons
Author-email: 521274311@qq.com
Classifier: Intended Audience :: Developers
Classifier: Programming Language :: Python :: 3.7
Classifier: Topic :: Software Development :: Libraries
